<annotation>
	<folder>images</folder>
	<filename>128.png</filename>
	<path>C:\Users\ruben\Documents\Github\bar-detection\images\128.png</path>
	<source>
		<database>Unknown</database>
	</source>
	<size>
		<width>800</width>
		<height>600</height>
		<depth>3</depth>
	</size>
	<segmented>0</segmented>
	<object>
		<name>barbell</name>
		<pose>Unspecified</pose>
		<truncated>0</truncated>
		<difficult>0</difficult>
		<bndbox>
			<xmin>221</xmin>
			<ymin>175</ymin>
			<xmax>521</xmax>
			<ymax>391</ymax>
		</bndbox>
	</object>
</annotation>
